skill_synonyms/LICENSE.md
skill_synonyms/README.md
skill_synonyms/__init__.py
skill_synonyms/skill.json
skill_synonyms/version.py
skill_synonyms/dialog/en-us/add_synonym_command.dialog
skill_synonyms/dialog/en-us/new_synonym_command.dialog
skill_synonyms/dialog/en-us/synonym_equals_command.dialog
skill_synonyms/dialog/en-us/synonym_pair_already_exists.dialog
skill_synonyms/neon_skill_synonyms.egg-info/PKG-INFO
skill_synonyms/neon_skill_synonyms.egg-info/SOURCES.txt
skill_synonyms/neon_skill_synonyms.egg-info/dependency_links.txt
skill_synonyms/neon_skill_synonyms.egg-info/entry_points.txt
skill_synonyms/neon_skill_synonyms.egg-info/requires.txt
skill_synonyms/neon_skill_synonyms.egg-info/top_level.txt
skill_synonyms/vocab/en-us/for.voc
skill_synonyms/vocab/en-us/particles.voc
skill_synonyms/vocab/en-us/set.voc
skill_synonyms/vocab/en-us/synonym.voc
neon_skill_synonyms-1.0.3.dist-info/LICENSE.md
neon_skill_synonyms-1.0.3.dist-info/METADATA
neon_skill_synonyms-1.0.3.dist-info/WHEEL
neon_skill_synonyms-1.0.3.dist-info/entry_points.txt
neon_skill_synonyms-1.0.3.dist-info/top_level.txt
neon_skill_synonyms-1.0.3.dist-info/RECORD
