Metadata-Version: 2.1
Name: neon-skill-synonyms
Version: 1.0.3
Home-page: https://github.com/NeonGeckoCom/skill-synonyms
Author: Neongecko
Author-email: developers@neon.ai
License: BSD-3-Clause
License-File: LICENSE.md
Requires-Dist: neon-utils~=1.12
Requires-Dist: ovos-utils>=0.0.28,~=0.0
Requires-Dist: ovos-bus-client>=0.0.3,~=0.0
